dmlib/__init__.py
dmlib-0.0.1.dist-info/LICENSE
dmlib-0.0.1.dist-info/METADATA
dmlib-0.0.1.dist-info/WHEEL
dmlib-0.0.1.dist-info/top_level.txt
dmlib-0.0.1.dist-info/RECORD
